ifast.py
iFastApi/__init__.py
iFastApi/ifast.py
iFastApi/api/BaseDataClass.py
iFastApi/api/BaseModel.py
iFastApi/api/BaseRoute.py
iFastApi/api/RoureManager.py
iFastApi/api/RouteInfo.py
iFastApi/api/__init__.py
iFastApi/db/BaseQuery.py
iFastApi/db/__init__.py
iFastApi/init_builder/__init__.py
iFastApi/init_builder/config/__init__.py
iFastApi/init_builder/model/__init__.py
iFastApi/jobs/__init__.py
iFastApi/mode/__init__.py
iFastApi/model/__init__.py
iFastApi/tests/__init__.py
iFastApi/tests/config.py
iFastApi/utils/__init__.py
iFastApi/utils/auto_builder.py
iFastApi/utils/code_pic.py
iFastApi/utils/functionPipe.py
iFastApi/utils/globals.py
iFastApi/utils/iResponse.py
iFastApi/utils/jwtToken.py
iFastApi/utils/singleton.py
iFastApi/utils/time.py
iFastApi/utils/toolfuns.py
ifastapi-0.0.3.31.19.5.data/data/init_builder.zip
init_builder/__init__.py
init_builder/abc/__init__.py
init_builder/api/__init__.py
init_builder/api/account.py
init_builder/config/__init__.py
init_builder/db/__init__.py
init_builder/db/account.py
init_builder/model/__init__.py
init_builder/model/account.py
tests/__init__.py
tests/config.py
ifastapi-0.0.3.31.19.5.dist-info/METADATA
ifastapi-0.0.3.31.19.5.dist-info/WHEEL
ifastapi-0.0.3.31.19.5.dist-info/entry_points.txt
ifastapi-0.0.3.31.19.5.dist-info/top_level.txt
ifastapi-0.0.3.31.19.5.dist-info/RECORD
